{
  "hash": "f005902a",
  "configHash": "54d59cee",
  "lockfileHash": "07f8244e",
  "browserHash": "3489aecc",
  "optimized": {
    "lucide-react": {
      "src": "../../node_modules/lucide-react/dist/esm/lucide-react.mjs",
      "file": "lucide-react.js",
      "fileHash": "2c078950",
      "needsInterop": false
    },
    "react-dom/client": {
      "src": "../../node_modules/react-dom/client.js",
      "file": "react-dom_client.js",
      "fileHash": "48925ced",
      "needsInterop": true
    },
    "react-router-dom": {
      "src": "../../node_modules/react-router-dom/dist/index.mjs",
      "file": "react-router-dom.js",
      "fileHash": "1dbb1a2d",
      "needsInterop": false
    },
    "react": {
      "src": "../../node_modules/react/index.js",
      "file": "react.js",
      "fileHash": "acc3ceb2",
      "needsInterop": true
    },
    "react/jsx-dev-runtime": {
      "src": "../../node_modules/react/jsx-dev-runtime.js",
      "file": "react_jsx-dev-runtime.js",
      "fileHash": "909f961c",
      "needsInterop": true
    },
    "recharts": {
      "src": "../../node_modules/recharts/es6/index.js",
      "file": "recharts.js",
      "fileHash": "70ea44f0",
      "needsInterop": false
    }
  },
  "chunks": {
    "react-B35R_oEX": {
      "file": "react-B35R_oEX.js",
      "isDynamicEntry": false
    },
    "react-dom-CYDThRfy": {
      "file": "react-dom-CYDThRfy.js",
      "isDynamicEntry": false
    }
  }
}